Workbook
Name TotalRevenue: Revenue!$B$1:$B$50
Name TotalCosts: Costs!$A$1:$A$30
Name ForecastRange: Forecast!$A$1:$C$20
Name BudgetYear: Summary!$A$1

Sheet Summary
A1: Budget 2024
A2: =SUM(B2:D2) | B2: 200 | C2: =Revenue!B2*0.8 | D2: =NOW()
A3: =SUM(B3:D3) | B3: 300 | C3: =Revenue!B3*0.8 | D3: =NOW()
A4: =SUM(B4:D4) | B4: 400 | C4: =Revenue!B4*0.8 | D4: =NOW()
A5: =SUM(B5:D5) | B5: 500 | C5: =Revenue!B5*0.8 | D5: =NOW()
A6: =SUM(B6:D6) | B6: 600 | C6: =Revenue!B6*0.8 | D6: =NOW()
A7: =SUM(B7:D7) | B7: 700 | C7: =Revenue!B7*0.8 | D7: =NOW()
A8: =SUM(B8:D8) | B8: 800 | C8: =Revenue!B8*0.8 | D8: =NOW()
A9: =SUM(B9:D9) | B9: 900 | C9: =Revenue!B9*0.8 | D9: =NOW()
A10: =SUM(B10:D10) | B10: 1000 | C10: =Revenue!B10*0.8 | D10: =NOW()
A11: =SUM(B11:D11) | B11: 1100 | C11: =Revenue!B11*0.8 | D11: =NOW()
A12: =SUM(B12:D12) | B12: 1200 | C12: =Revenue!B12*0.8 | D12: =NOW()
A13: =SUM(B13:D13) | B13: 1300 | C13: =Revenue!B13*0.8 | D13: =NOW()
... A39: =SUM(B39:D39) | B39: 3900 | C39: =Revenue!B39*0.8 | D39: =NOW()

Sheet Revenue
A1: Item 1 | B1: 250 | C1: =Summary!A1 | D1: =TODAY()
A2: Item 2 | B2: 500 | C2: =Summary!A2 | D2: =TODAY()
A3: Item 3 | B3: 750 | C3: =Summary!A3 | D3: =TODAY()
A4: Item 4 | B4: 1000 | C4: =Summary!A4 | D4: =TODAY()
A5: Item 5 | B5: 1250 | C5: =Summary!A5 | D5: =TODAY()
A6: Item 6 | B6: 1500 | C6: =Summary!A6 | D6: =TODAY()
A7: Item 7 | B7: 1750 | C7: =Summary!A7 | D7: =TODAY()
A8: Item 8 | B8: 2000 | C8: =Summary!A8 | D8: =TODAY()
A9: Item 9 | B9: 2250 | C9: =Summary!A9 | D9: =TODAY()
A10: Item 10 | B10: 2500 | C10: =Summary!A10 | D10: =TODAY()
A11: Item 11 | B11: 2750 | C11: =Summary!A11 | D11: =TODAY()
A12: Item 12 | B12: 3000 | C12: =Summary!A12 | D12: =TODAY()
... A49: Item 49 | B49: 12250 | C49: =Summary!A49 | D49: =TODAY()

Sheet Costs
A1: =Revenue!B1*0.3 | B1: =Summary!A1
A2: =Revenue!B2*0.3 | B2: =Summary!A2
A3: =Revenue!B3*0.3 | B3: =Summary!A3
A4: =Revenue!B4*0.3 | B4: =Summary!A4
A5: =Revenue!B5*0.3 | B5: =Summary!A5
A6: =Revenue!B6*0.3 | B6: =Summary!A6
A7: =Revenue!B7*0.3 | B7: =Summary!A7
A8: =Revenue!B8*0.3 | B8: =Summary!A8
A9: =Revenue!B9*0.3 | B9: =Summary!A9
A10: =Revenue!B10*0.3 | B10: =Summary!A10
A11: =Revenue!B11*0.3 | B11: =Summary!A11
A12: =Revenue!B12*0.3 | B12: =Summary!A12
... A29: =Revenue!B29*0.3 | B29: =Summary!A29

Sheet Forecast
A1: =RAND() | B1: =Revenue!B1+Costs!A1 | C1: =[External_Model.xlsx]Assumptions!C1
A2: =RAND() | B2: =Revenue!B2+Costs!A2 | C2: =[External_Model.xlsx]Assumptions!C2
A3: =RAND() | B3: =Revenue!B3+Costs!A3 | C3: =[External_Model.xlsx]Assumptions!C3
A4: =RAND() | B4: =Revenue!B4+Costs!A4 | C4: =[External_Model.xlsx]Assumptions!C4
A5: =RAND() | B5: =Revenue!B5+Costs!A5 | C5: =[External_Model.xlsx]Assumptions!C5
A6: =RAND() | B6: =Revenue!B6+Costs!A6 | C6: =[External_Model.xlsx]Assumptions!C6
A7: =RAND() | B7: =Revenue!B7+Costs!A7 | C7: =[External_Model.xlsx]Assumptions!C7
A8: =RAND() | B8: =Revenue!B8+Costs!A8 | C8: =[External_Model.xlsx]Assumptions!C8
A9: =RAND() | B9: =Revenue!B9+Costs!A9 | C9: =[External_Model.xlsx]Assumptions!C9
A10: =RAND() | B10: =Revenue!B10+Costs!A10 | C10: =[External_Model.xlsx]Assumptions!C10
A11: =RAND() | B11: =Revenue!B11+Costs!A11 | C11: =[External_Model.xlsx]Assumptions!C11
A12: =RAND() | B12: =Revenue!B12+Costs!A12 | C12: =[External_Model.xlsx]Assumptions!C12
... A19: =RAND() | B19: =Revenue!B19+Costs!A19 | C19: =[External_Model.xlsx]Assumptions!C19

Sheet Validation

Sheet Archive
